<?xml version="1.0" encoding="utf-8"?>
<edmx:Edmx Version="1.0" xmlns:edmx="http://schemas.microsoft.com/ado/2007/06/edmx" xmlns:m="http://schemas.microsoft.com/ado/2007/08/dataservices/metadata" xmlns:sap="http://www.sap.com/Protocols/SAPData">
    <edmx:DataServices m:DataServiceVersion="2.0">
        <Schema Namespace="ZGW_WH_ODATA_SRV" xml:lang="de" sap:schema-version="1" xmlns="http://schemas.microsoft.com/ado/2008/09/edm">
            <Annotation Term="Core.SchemaVersion" String="1.0.0" xmlns="http://docs.oasis-open.org/odata/ns/edm"/>
            <EntityType Name="Material" sap:content-version="1">
                <Key>
                    <PropertyRef Name="MaterialId"/>
                </Key>
                <Property Name="MaterialId" Type="Edm.String" Nullable="false" MaxLength="40" sap:unicode="false" sap:label="Material" sap:creatable="false" sap:updatable="false" sap:sortable="true" sap:filterable="true"/>
                <Property Name="MaterialName" Type="Edm.String" Nullable="false" MaxLength="40" sap:unicode="false" sap:label="Description" sap:creatable="false" sap:updatable="false" sap:sortable="true" sap:filterable="true"/>
                <Property Name="MaterialType" Type="Edm.String" Nullable="false" MaxLength="4" sap:unicode="false" sap:label="Material Type" sap:creatable="false" sap:updatable="false" sap:sortable="false" sap:filterable="false"/>
                <Property Name="BaseUnit" Type="Edm.String" Nullable="false" MaxLength="3" sap:unicode="false" sap:label="Base Unit" sap:creatable="false" sap:updatable="false" sap:sortable="false" sap:filterable="false" sap:semantics="unit-of-measure"/>
                <Property Name="Plant" Type="Edm.String" Nullable="false" MaxLength="4" sap:unicode="false" sap:label="Plant" sap:creatable="false" sap:updatable="false" sap:sortable="false" sap:filterable="false"/>
                <Property Name="StorageLocation" Type="Edm.String" Nullable="false" MaxLength="4" sap:unicode="false" sap:label="Location" sap:creatable="false" sap:updatable="false" sap:sortable="false" sap:filterable="false"/>
            </EntityType>
            <EntityType Name="Stock" sap:content-version="1">
                <Key>
                    <PropertyRef Name="MaterialId"/>
                    <PropertyRef Name="Plant"/>
                    <PropertyRef Name="StorageLocation"/>
                </Key>
                <Property Name="MaterialId" Type="Edm.String" Nullable="false" MaxLength="40" sap:unicode="false" sap:label="Material" sap:creatable="false" sap:updatable="false" sap:sortable="false" sap:filterable="false"/>
                <Property Name="Plant" Type="Edm.String" Nullable="false" MaxLength="4" sap:unicode="false" sap:label="Werk" sap:creatable="false" sap:updatable="false" sap:sortable="false" sap:filterable="false"/>
                <Property Name="StorageLocation" Type="Edm.String" Nullable="false" MaxLength="4" sap:unicode="false" sap:label="Lagerort" sap:creatable="false" sap:updatable="false" sap:sortable="false" sap:filterable="false"/>
                <Property Name="Quantity" Type="Edm.Decimal" Nullable="false" Precision="13" Scale="3" sap:unicode="false" sap:unit="BaseUnit" sap:label="Frei verwendbar" sap:creatable="false" sap:updatable="false" sap:sortable="false" sap:filterable="false"/>
                <Property Name="BaseUnit" Type="Edm.String" Nullable="false" MaxLength="3" sap:unicode="false" sap:label="Basis-ME" sap:creatable="false" sap:updatable="false" sap:sortable="false" sap:filterable="false" sap:semantics="unit-of-measure"/>
                <Property Name="MaterialName" Type="Edm.String" Nullable="false" MaxLength="40" sap:unicode="false" sap:label="Bezeichnung" sap:creatable="false" sap:updatable="false" sap:sortable="false" sap:filterable="false"/>
            </EntityType>
            <EntityType Name="GoodsReceipt" sap:content-version="1">
                <Key>
                    <PropertyRef Name="MaterialId"/>
                </Key>
                <Property Name="MaterialId" Type="Edm.String" Nullable="false" MaxLength="40" sap:unicode="false" sap:label="Material" sap:creatable="false" sap:updatable="false" sap:sortable="false" sap:filterable="false"/>
                <Property Name="Plant" Type="Edm.String" Nullable="false" MaxLength="4" sap:unicode="false" sap:label="Werk" sap:creatable="false" sap:updatable="false" sap:sortable="false" sap:filterable="false"/>
                <Property Name="StorageLocation" Type="Edm.String" Nullable="false" MaxLength="4" sap:unicode="false" sap:label="Lagerort" sap:creatable="false" sap:updatable="false" sap:sortable="false" sap:filterable="false"/>
                <Property Name="Quantity" Type="Edm.Decimal" Nullable="false" Precision="13" Scale="3" sap:unicode="false" sap:label="Menge" sap:creatable="false" sap:updatable="false" sap:sortable="false" sap:filterable="false"/>
                <Property Name="PostingDate" Type="Edm.DateTime" Nullable="false" Precision="7" sap:unicode="false" sap:label="Buchungsdatum" sap:creatable="false" sap:updatable="false" sap:sortable="false" sap:filterable="false"/>
                <Property Name="DocumentDate" Type="Edm.DateTime" Nullable="false" Precision="7" sap:unicode="false" sap:label="Belegdatum" sap:creatable="false" sap:updatable="false" sap:sortable="false" sap:filterable="false"/>
                <Property Name="Remark" Type="Edm.String" Nullable="false" MaxLength="255" sap:unicode="false" sap:creatable="false" sap:updatable="false" sap:sortable="false" sap:filterable="false"/>
                <Property Name="MaterialDocument" Type="Edm.String" Nullable="false" MaxLength="20" sap:unicode="false" sap:creatable="false" sap:updatable="false" sap:sortable="false" sap:filterable="false"/>
                <Property Name="Status" Type="Edm.String" Nullable="false" MaxLength="10" sap:unicode="false" sap:creatable="false" sap:updatable="false" sap:sortable="false" sap:filterable="false"/>
                <Property Name="Message" Type="Edm.String" Nullable="false" MaxLength="255" sap:unicode="false" sap:creatable="false" sap:updatable="false" sap:sortable="false" sap:filterable="false"/>
            </EntityType>
            <EntityType Name="DashboardKPI" sap:content-version="1">
                <Key>
                    <PropertyRef Name="Id"/>
                </Key>
                <Property Name="Id" Type="Edm.String" Nullable="false" MaxLength="1" sap:unicode="false" sap:label="ID" sap:creatable="false" sap:updatable="false" sap:sortable="true" sap:filterable="true"/>
                <Property Name="TotalMaterials" Type="Edm.Int32" Nullable="false" sap:unicode="false" sap:label="Total Materials" sap:creatable="false" sap:updatable="false" sap:sortable="false" sap:filterable="false"/>
                <Property Name="TotalStock" Type="Edm.Decimal" Nullable="false" Precision="13" Scale="3" sap:unicode="false" sap:label="Total Stock" sap:creatable="false" sap:updatable="false" sap:sortable="false" sap:filterable="false"/>
                <Property Name="LowStockCount" Type="Edm.Int32" Nullable="false" sap:unicode="false" sap:label="Low Stock Alert" sap:creatable="false" sap:updatable="false" sap:sortable="false" sap:filterable="false"/>
                <Property Name="TotalPlants" Type="Edm.Int32" Nullable="false" sap:unicode="false" sap:label="Total Plants" sap:creatable="false" sap:updatable="false" sap:sortable="false" sap:filterable="false"/>
            </EntityType>
            <EntityType Name="History" sap:content-version="1">
                <Key>
                    <PropertyRef Name="MaterialDocument"/>
                    <PropertyRef Name="Year"/>
                    <PropertyRef Name="MaterialId"/>
                </Key>
                <Property Name="MaterialDocument" Type="Edm.String" Nullable="false" MaxLength="10" sap:unicode="false" sap:label="Material Document" sap:creatable="false" sap:updatable="false" sap:sortable="true" sap:filterable="true"/>
                <Property Name="Year" Type="Edm.String" Nullable="false" MaxLength="4" sap:unicode="false" sap:label="Year" sap:creatable="false" sap:updatable="false" sap:sortable="true" sap:filterable="true"/>
                <Property Name="PostingDate" Type="Edm.DateTime" Nullable="false" Precision="7" sap:unicode="false" sap:label="Posting Date" sap:creatable="false" sap:updatable="false" sap:sortable="true" sap:filterable="true"/>
                <Property Name="MaterialId" Type="Edm.String" Nullable="false" MaxLength="40" sap:unicode="false" sap:label="Material" sap:creatable="false" sap:updatable="false" sap:sortable="true" sap:filterable="true"/>
                <Property Name="MovementType" Type="Edm.String" Nullable="false" MaxLength="3" sap:unicode="false" sap:label="Movement Type" sap:creatable="false" sap:updatable="false" sap:sortable="false" sap:filterable="false"/>
                <Property Name="BaseUnit" Type="Edm.String" Nullable="false" MaxLength="3" sap:unicode="false" sap:label="Base Unit" sap:creatable="false" sap:updatable="false" sap:sortable="false" sap:filterable="false" sap:semantics="unit-of-measure"/>
                <Property Name="Quantity" Type="Edm.Decimal" Nullable="false" Precision="13" Scale="3" sap:unicode="false" sap:label="Quantity" sap:creatable="false" sap:updatable="false" sap:sortable="false" sap:filterable="false"/>
                <Property Name="Plant" Type="Edm.String" Nullable="false" MaxLength="4" sap:unicode="false" sap:label="Plant" sap:creatable="false" sap:updatable="false" sap:sortable="false" sap:filterable="false"/>
                <Property Name="StorageLocation" Type="Edm.String" Nullable="false" MaxLength="4" sap:unicode="false" sap:label="Location" sap:creatable="false" sap:updatable="false" sap:sortable="false" sap:filterable="false"/>
                <Property Name="MaterialName" Type="Edm.String" Nullable="false" MaxLength="40" sap:unicode="false" sap:label="Description" sap:creatable="false" sap:updatable="false" sap:sortable="false" sap:filterable="false"/>
                <Property Name="Status" Type="Edm.String" Nullable="false" MaxLength="10" sap:unicode="false" sap:creatable="false" sap:updatable="false" sap:sortable="false" sap:filterable="false"/>
                <Property Name="Remark" Type="Edm.String" Nullable="false" MaxLength="255" sap:unicode="false" sap:creatable="false" sap:updatable="false" sap:sortable="false" sap:filterable="false"/>
                <Property Name="DocumentDate" Type="Edm.DateTime" Nullable="false" Precision="7" sap:unicode="false" sap:label="Document Date" sap:creatable="false" sap:updatable="false" sap:sortable="false" sap:filterable="false"/>
            </EntityType>
            <EntityType Name="PlantMaster" sap:content-version="1">
                <Key>
                    <PropertyRef Name="PlantId"/>
                </Key>
                <Property Name="PlantId" Type="Edm.String" Nullable="false" MaxLength="4" sap:unicode="false" sap:label="Plant ID" sap:creatable="false" sap:updatable="false" sap:sortable="true" sap:filterable="true"/>
                <Property Name="PlantName" Type="Edm.String" Nullable="false" MaxLength="30" sap:unicode="false" sap:label="Plant Name" sap:creatable="false" sap:updatable="false" sap:sortable="true" sap:filterable="true"/>
            </EntityType>
            <EntityType Name="StorageLocationMaster" sap:content-version="1">
                <Key>
                    <PropertyRef Name="PlantId"/>
                    <PropertyRef Name="StorageLocationId"/>
                </Key>
                <Property Name="PlantId" Type="Edm.String" Nullable="false" MaxLength="4" sap:unicode="false" sap:label="Plant" sap:creatable="false" sap:updatable="false" sap:sortable="true" sap:filterable="true"/>
                <Property Name="StorageLocationId" Type="Edm.String" Nullable="false" MaxLength="4" sap:unicode="false" sap:label="Location" sap:creatable="false" sap:updatable="false" sap:sortable="true" sap:filterable="true"/>
                <Property Name="StorageLocationName" Type="Edm.String" Nullable="false" MaxLength="16" sap:unicode="false" sap:label="Location Name" sap:creatable="false" sap:updatable="false" sap:sortable="true" sap:filterable="true"/>
            </EntityType>
            <EntityContainer Name="ZGW_WH_ODATA_SRV_Entities" m:IsDefaultEntityContainer="true" sap:supported-formats="atom json xlsx">
                <EntitySet Name="MaterialSet" EntityType="ZGW_WH_ODATA_SRV.Material" sap:creatable="false" sap:updatable="false" sap:deletable="false" sap:pageable="false" sap:content-version="1"/>
                <EntitySet Name="StockSet" EntityType="ZGW_WH_ODATA_SRV.Stock" sap:creatable="false" sap:updatable="false" sap:deletable="false" sap:pageable="false" sap:content-version="1"/>
                <EntitySet Name="GoodsReceiptSet" EntityType="ZGW_WH_ODATA_SRV.GoodsReceipt" sap:creatable="false" sap:updatable="false" sap:deletable="false" sap:pageable="false" sap:content-version="1"/>
                <EntitySet Name="DashboardKPISet" EntityType="ZGW_WH_ODATA_SRV.DashboardKPI" sap:creatable="false" sap:updatable="false" sap:deletable="false" sap:pageable="false" sap:content-version="1"/>
                <EntitySet Name="HistorySet" EntityType="ZGW_WH_ODATA_SRV.History" sap:creatable="false" sap:updatable="false" sap:deletable="false" sap:pageable="false" sap:content-version="1"/>
                <EntitySet Name="PlantMasterSet" EntityType="ZGW_WH_ODATA_SRV.PlantMaster" sap:creatable="false" sap:updatable="false" sap:deletable="false" sap:pageable="false" sap:content-version="1"/>
                <EntitySet Name="StorageLocationMasterSet" EntityType="ZGW_WH_ODATA_SRV.StorageLocationMaster" sap:creatable="false" sap:updatable="false" sap:deletable="false" sap:pageable="false" sap:content-version="1"/>
            </EntityContainer>
            <atom:link rel="self" href="https://s40lp1.ucc.cit.tum.de/sap/opu/odata/sap/ZGW_WH_ODATA_SRV/$metadata" xmlns:atom="http://www.w3.org/2005/Atom"/>
            <atom:link rel="latest-version" href="https://s40lp1.ucc.cit.tum.de/sap/opu/odata/sap/ZGW_WH_ODATA_SRV/$metadata" xmlns:atom="http://www.w3.org/2005/Atom"/>
        </Schema>
    </edmx:DataServices>
</edmx:Edmx>